orcatools/__init__.py
orcatools/__main__.py
orcatools/go.py
orcatools/neb.py
orcatools-0.0.2.dist-info/LICENSE
orcatools-0.0.2.dist-info/METADATA
orcatools-0.0.2.dist-info/WHEEL
orcatools-0.0.2.dist-info/top_level.txt
orcatools-0.0.2.dist-info/RECORD
