Metadata-Version: 2.1
Name: orcatools
Version: 0.0.2
Summary: Python tools for ORCA
Home-page: https://github.com/Tonner-Zech-Group/ORCA-tools
Author: Patrick Melix
Author-email: Patrick Melix <patrick.melix@uni-leipzig.de>
Project-URL: Homepage, https://github.com/Tonner-Zech-Group/ORCA-tools
Project-URL: Issues, https://github.com/Tonner-Zech-Group/ORCA-tools/issues
Classifier: Programming Language :: Python :: 3
Classifier: License :: OSI Approved :: MIT License
Classifier: Operating System :: OS Independent
Requires-Python: >=3.8
License-File: LICENSE
